chisel/__init__.py
chisel/auth.py
chisel/cached_files.py
chisel/cli.py
chisel/constants.py
chisel/spinner.py
chisel/trace.py
chisel_cli-0.1.33.dist-info/licenses/LICENSE
chisel_cli-0.1.33.dist-info/METADATA
chisel_cli-0.1.33.dist-info/WHEEL
chisel_cli-0.1.33.dist-info/entry_points.txt
chisel_cli-0.1.33.dist-info/top_level.txt
chisel_cli-0.1.33.dist-info/RECORD
