Metadata-Version: 2.4
Name: chisel-cli
Version: 0.1.33
Summary: Chisel CLI - Accelerate your Python functions with cloud GPUs
Author-email: Herdora <contact@herdora.com>
License: MIT
Project-URL: Homepage, https://github.com/Herdora/chisel
Project-URL: Repository, https://github.com/Herdora/chisel.git
Project-URL: Issues, https://github.com/Herdora/chisel/issues
Classifier: Development Status :: 3 - Alpha
Classifier: Intended Audience :: Developers
Classifier: License :: OSI Approved :: MIT License
Classifier: Programming Language :: Python :: 3
Classifier: Programming Language :: Python :: 3.8
Classifier: Programming Language :: Python :: 3.9
Classifier: Programming Language :: Python :: 3.10
Classifier: Programming Language :: Python :: 3.11
Classifier: Programming Language :: Python :: 3.12
Requires-Python: >=3.8
License-File: LICENSE
Requires-Dist: requests>=2.25.0
Requires-Dist: click>=8.0.0
Requires-Dist: rich>=13.0.0
Provides-Extra: dev
Requires-Dist: pytest>=6.0; extra == "dev"
Requires-Dist: ruff>=0.1.0; extra == "dev"
Dynamic: license-file
